<?xml version="1.0" encoding="utf-8"?>
<BattleCardDescRoot xmlns:xsi="http://www.w3.org/2001/XMLSchema-instance" xmlns:xsd="http://www.w3.org/2001/XMLSchema">
  <cardDescList>
    <BattleCardDesc ID="-10">
      <LocalizedName>교활한 회피</LocalizedName> <!-- Roguish Evade -->
    </BattleCardDesc>
    <BattleCardDesc ID="-11">
      <LocalizedName>이중 타격</LocalizedName> <!-- Twin Strikes -->
    </BattleCardDesc>
    <BattleCardDesc ID="-12">
      <LocalizedName>굳건한 방어</LocalizedName> <!-- Stand Ground -->
    </BattleCardDesc>
    <BattleCardDesc ID="-13">
      <LocalizedName>치고 빠지기</LocalizedName> <!-- Hit and Run -->
    </BattleCardDesc>
	<BattleCardDesc ID="-14">
      <LocalizedName>연계 타격</LocalizedName> <!-- Coordinated Strikes -->
    </BattleCardDesc>
  </cardDescList>
</BattleCardDescRoot>
